Metadata-Version: 1.0
Name: calculi
Version: 0.1
Summary: Gaussian and Binomial distributions
Home-page: UNKNOWN
Author: Saviour Eking
Author-email: UNKNOWN
License: UNKNOWN
Platform: UNKNOWN
